uvpg/__init__.py
uvpg/main.py
uvpg/templates.py
uvpg-1.1.4.dist-info/METADATA
uvpg-1.1.4.dist-info/WHEEL
uvpg-1.1.4.dist-info/entry_points.txt
uvpg-1.1.4.dist-info/licenses/LICENSE
uvpg-1.1.4.dist-info/RECORD
