Metadata-Version: 2.4
Name: uvpg
Version: 1.1.4
Summary: UV Project Generator - Create Python monorepos with workspaces.
Project-URL: repository, https://github.com/lucasmaziero/uvpg
Author-email: Lucas Maziero <lucas.mazie.ro@hotmail.com>
License-Expression: MIT
License-File: LICENSE
Requires-Python: >=3.12
